SpamFilter/__init__.py
SpamFilter/antispam.py
discordpy_antispam-1.0.3.dist-info/LICENSE
discordpy_antispam-1.0.3.dist-info/METADATA
discordpy_antispam-1.0.3.dist-info/WHEEL
discordpy_antispam-1.0.3.dist-info/top_level.txt
discordpy_antispam-1.0.3.dist-info/RECORD
