Metadata-Version: 2.1
Name: discordpy-antispam
Version: 1.0.3
Summary: An efficient and simple anti-spam system made for your discord bots.
Home-page: https://github.com/DorianAarno/SpamFilter
Download-URL: https://github.com/DorianAarno/SpamFilter/archive/refs/tags/v1.0.2.tar.gz
Author: Aarno Dorian
Author-email: aarnodorian56@gmail.com
License: MIT
Classifier: Intended Audience :: Developers
Classifier: Natural Language :: English
Classifier: Operating System :: OS Independent
Classifier: Programming Language :: Python :: 3.8
Classifier: Programming Language :: Python :: 3.9
Classifier: Topic :: Internet
Classifier: Topic :: Software Development :: Libraries
Classifier: Topic :: Software Development :: Libraries :: Python Modules
Classifier: Topic :: Utilities
Classifier: Typing :: Typed
License-File: LICENSE
Requires-Dist: nltk
